kitconcept.richpage-2.0.0-py3.10-nspkg.pth
kitconcept/richpage/__init__.py
kitconcept/richpage/configure.zcml
kitconcept/richpage/interfaces.py
kitconcept/richpage/setuphandlers.py
kitconcept/richpage/testing.py
kitconcept/richpage/upgrades.zcml
kitconcept/richpage/browser/__init__.py
kitconcept/richpage/browser/configure.zcml
kitconcept/richpage/browser/item.pt
kitconcept/richpage/browser/overrides/.gitkeep
kitconcept/richpage/browser/static/.gitkeep
kitconcept/richpage/content/__init__.py
kitconcept/richpage/content/audio.py
kitconcept/richpage/content/file.py
kitconcept/richpage/content/googlemap.py
kitconcept/richpage/content/image.py
kitconcept/richpage/content/richpage.py
kitconcept/richpage/content/slideshow.py
kitconcept/richpage/content/text.py
kitconcept/richpage/content/video.py
kitconcept/richpage/locales/kitconcept.richpage.pot
kitconcept/richpage/locales/update.sh
kitconcept/richpage/profiles/default/browserlayer.xml
kitconcept/richpage/profiles/default/metadata.xml
kitconcept/richpage/profiles/default/types.xml
kitconcept/richpage/profiles/default/types/Audio.xml
kitconcept/richpage/profiles/default/types/GoogleMap.xml
kitconcept/richpage/profiles/default/types/RichPage.xml
kitconcept/richpage/profiles/default/types/RichPageFile.xml
kitconcept/richpage/profiles/default/types/RichPageImage.xml
kitconcept/richpage/profiles/default/types/RichPageText.xml
kitconcept/richpage/profiles/default/types/Slideshow.xml
kitconcept/richpage/profiles/default/types/Video.xml
kitconcept/richpage/profiles/uninstall/browserlayer.xml
kitconcept/richpage/tests/__init__.py
kitconcept/richpage/tests/test_content.py
kitconcept.richpage-2.0.0.dist-info/LICENSE.txt
kitconcept.richpage-2.0.0.dist-info/METADATA
kitconcept.richpage-2.0.0.dist-info/WHEEL
kitconcept.richpage-2.0.0.dist-info/entry_points.txt
kitconcept.richpage-2.0.0.dist-info/namespace_packages.txt
kitconcept.richpage-2.0.0.dist-info/top_level.txt
kitconcept.richpage-2.0.0.dist-info/RECORD
