Metadata-Version: 2.1
Name: kitconcept.richpage
Version: 2.0.0
Summary: Folderish page with rich content
Home-page: https://github.com/kitconcept/kitconcept.richpage
Author: kitconcept GmbH
Author-email: info@kitconcept.com
License: GPL version 2
Project-URL: PyPI, https://pypi.python.org/pypi/kitconcept.richpage
Project-URL: Source, https://github.com/kitconcept/kitconcept.richpage
Project-URL: Tracker, https://github.com/kitconcept/kitconcept.richpage/issues
Keywords: Python Plone
Classifier: Development Status :: 5 - Production/Stable
Classifier: Environment :: Web Environment
Classifier: Framework :: Plone :: 5.2
Classifier: Framework :: Plone :: 6.0
Classifier: Framework :: Plone
Classifier: License :: OSI Approved :: GNU General Public License v2 (GPLv2)
Classifier: Operating System :: OS Independent
Classifier: Programming Language :: Python :: 3.10
Classifier: Programming Language :: Python :: 3.11
Classifier: Programming Language :: Python :: 3.7
Classifier: Programming Language :: Python :: 3.8
Classifier: Programming Language :: Python :: 3.9
Classifier: Programming Language :: Python
License-File: LICENSE.txt
Requires-Dist: Plone
Requires-Dist: setuptools (>=36.2)
Requires-Dist: z3c.jbot
Requires-Dist: collective.dexteritytextindexer
Provides-Extra: test
Requires-Dist: plone.app.testing ; extra == 'test'
Requires-Dist: plone.app.contenttypes ; extra == 'test'
Requires-Dist: plone.app.robotframework ; extra == 'test'
